Flask_Restless_jcrben-1.0.0b2.dev0.dist-info/METADATA
Flask_Restless_jcrben-1.0.0b2.dev0.dist-info/RECORD
Flask_Restless_jcrben-1.0.0b2.dev0.dist-info/WHEEL
Flask_Restless_jcrben-1.0.0b2.dev0.dist-info/top_level.txt
flask_restless/__init__.py
flask_restless/helpers.py
flask_restless/manager.py
flask_restless/search/__init__.py
flask_restless/search/drivers.py
flask_restless/search/filters.py
flask_restless/search/operators.py
flask_restless/serialization/__init__.py
flask_restless/serialization/deserializers.py
flask_restless/serialization/exceptions.py
flask_restless/serialization/serializers.py
flask_restless/views/__init__.py
flask_restless/views/base.py
flask_restless/views/function.py
flask_restless/views/helpers.py
flask_restless/views/relationships.py
flask_restless/views/resources.py
