Metadata-Version: 2.1
Name: Flask-Restless-jcrben
Version: 1.0.0b2.dev0
Summary: Flask extension for generating a JSON API interface for SQLAlchemy models
Home-page: https://github.com/jfinkels/flask-restless
Author: Jeffrey Finkelstein
Author-email: jeffrey.finkelstein@gmail.com
License: GNU AGPLv3+ or BSD
Download-URL: https://pypi.python.org/pypi/Flask-Restless
Keywords: ReST,API,Flask
Platform: any
Classifier: Development Status :: 4 - Beta
Classifier: Environment :: Web Environment
Classifier: Intended Audience :: Developers
Classifier: License :: OSI Approved :: BSD License
Classifier: License :: OSI Approved :: GNU Affero General Public License v3 or later (AGPLv3+)
Classifier: Operating System :: OS Independent
Classifier: Programming Language :: Python
Classifier: Programming Language :: Python :: 2
Classifier: Programming Language :: Python :: 2.6
Classifier: Programming Language :: Python :: 2.7
Classifier: Programming Language :: Python :: 3
Classifier: Programming Language :: Python :: 3.3
Classifier: Programming Language :: Python :: 3.4
Classifier: Programming Language :: Python :: 3.5
Classifier: Topic :: Database :: Front-Ends
Classifier: Topic :: Internet :: WWW/HTTP
Classifier: Topic :: Software Development :: Libraries :: Python Modules
Requires-Dist: flask (>=0.10)
Requires-Dist: sqlalchemy (>=0.8)
Requires-Dist: python-dateutil (>2.2)
